{
  "cli": {
    "version": ">= 16.25.0",
    "appVersionSource": "remote"
  },
  "build": {
    "development": {
      "developmentClient": true,
      "distribution": "internal",
      "android": {
        "buildType": "apk"
      },
      "workingDirectory": "rebookingSystem"
    },
    "preview": {
      "distribution": "internal",
      "android": {
        "buildType": "apk"
      },
      "workingDirectory": "rebookingSystem"
    },
    "production": {
      "distribution": "store",
      "android": {
        "buildType": "app-bundle"
      },
      "workingDirectory": "rebookingSystem"
    }
  }
}